bisheng_unstructured/__init__.py
bisheng_unstructured/__version__.py
bisheng_unstructured/logger.py
bisheng_unstructured/utils.py
bisheng_unstructured/api/__init__.py
bisheng_unstructured/api/any2pdf.py
bisheng_unstructured/api/main.py
bisheng_unstructured/api/pipeline.py
bisheng_unstructured/api/types.py
bisheng_unstructured/cleaners/__init__.py
bisheng_unstructured/cleaners/core.py
bisheng_unstructured/cleaners/extract.py
bisheng_unstructured/cleaners/translate.py
bisheng_unstructured/common/__init__.py
bisheng_unstructured/common/logger.py
bisheng_unstructured/common/timer.py
bisheng_unstructured/documents/__init__.py
bisheng_unstructured/documents/base.py
bisheng_unstructured/documents/coordinates.py
bisheng_unstructured/documents/elements.py
bisheng_unstructured/documents/email_elements.py
bisheng_unstructured/documents/html.py
bisheng_unstructured/documents/html_utils.py
bisheng_unstructured/documents/layout.py
bisheng_unstructured/documents/markdown.py
bisheng_unstructured/documents/xml.py
bisheng_unstructured/documents/pdf_parser/__init__.py
bisheng_unstructured/documents/pdf_parser/blob.py
bisheng_unstructured/documents/pdf_parser/image.py
bisheng_unstructured/documents/pdf_parser/pdf.py
bisheng_unstructured/documents/pdf_parser/pdf_creator.py
bisheng_unstructured/documents/pdf_parser/test_pdf.py
bisheng_unstructured/file_utils/__init__.py
bisheng_unstructured/file_utils/encoding.py
bisheng_unstructured/file_utils/exploration.py
bisheng_unstructured/file_utils/file_conversion.py
bisheng_unstructured/file_utils/filetype.py
bisheng_unstructured/file_utils/google_filetype.py
bisheng_unstructured/file_utils/metadata.py
bisheng_unstructured/models/__init__.py
bisheng_unstructured/models/common.py
bisheng_unstructured/models/formula_agent.py
bisheng_unstructured/models/layout_agent.py
bisheng_unstructured/models/ocr_agent.py
bisheng_unstructured/models/table_agent.py
bisheng_unstructured/nlp/__init__.py
bisheng_unstructured/nlp/english-words.txt
bisheng_unstructured-0.0.3.post4.dist-info/LICENSE
bisheng_unstructured-0.0.3.post4.dist-info/METADATA
bisheng_unstructured-0.0.3.post4.dist-info/WHEEL
bisheng_unstructured-0.0.3.post4.dist-info/top_level.txt
bisheng_unstructured-0.0.3.post4.dist-info/RECORD
